Classfile /F:/dev/geektime/java½ø½×ÑµÁ·Óª-ÇØ½ðÎÀ/JAVA-01/Week_01/code/Hello.class
  Last modified 2021-1-11; size 575 bytes
  MD5 checksum 5a826fe80061372f0019a0df24ca163d
  Compiled from "Hello.java"
public class Hello
  minor version: 0
  major version: 52
  flags: ACC_PUBLIC, ACC_SUPER
Constant pool:
   #1 = Methodref          #13.#24        // java/lang/Object."<init>":()V
   #2 = Methodref          #12.#25        // Hello.testBasicType:()V
   #3 = Long               4l
   #5 = Float              5.5f
   #6 = Double             6.6d
   #8 = Long               50l
  #10 = Long               30l
  #12 = Class              #26            // Hello
  #13 = Class              #27            // java/lang/Object
  #14 = Utf8               <init>
  #15 = Utf8               ()V
  #16 = Utf8               Code
  #17 = Utf8               LineNumberTable
  #18 = Utf8               main
  #19 = Utf8               ([Ljava/lang/String;)V
  #20 = Utf8               testBasicType
  #21 = Utf8               testArithmetic
  #22 = Utf8               SourceFile
  #23 = Utf8               Hello.java
  #24 = NameAndType        #14:#15        // "<init>":()V
  #25 = NameAndType        #20:#15        // testBasicType:()V
  #26 = Utf8               Hello
  #27 = Utf8               java/lang/Object
{
  public Hello();
    descriptor: ()V
    flags: ACC_PUBLIC
    Code:
      stack=1, locals=1, args_size=1
         0: aload_0
         1: invokespecial #1                  // Method java/lang/Object."<init>":()V
         4: return
      LineNumberTable:
        line 6: 0

  public static void main(java.lang.String[]);
    descriptor: ([Ljava/lang/String;)V
    flags: ACC_PUBLIC, ACC_STATIC
    Code:
      stack=0, locals=1, args_size=1
         0: invokestatic  #2                  // Method testBasicType:()V
         3: return
      LineNumberTable:
        line 8: 0
        line 9: 3

  public static void testBasicType();
    descriptor: ()V
    flags: ACC_PUBLIC, ACC_STATIC
    Code:
      stack=2, locals=9, args_size=0
         0: iconst_1
         1: istore_0
         2: iconst_2
         3: istore_1
         4: iconst_3
         5: istore_2
         6: ldc2_w        #3                  // long 4l
         9: lstore_3
        10: ldc           #5                  // float 5.5f
        12: fstore        5
        14: ldc2_w        #6                  // double 6.6d
        17: dstore        6
        19: bipush        65
        21: istore        8
        23: return
      LineNumberTable:
        line 15: 0
        line 16: 2
        line 17: 4
        line 18: 6
        line 19: 10
        line 20: 14
        line 21: 19
        line 22: 23

  public static void testArithmetic();
    descriptor: ()V
    flags: ACC_PUBLIC, ACC_STATIC
    Code:
      stack=4, locals=15, args_size=0
         0: iconst_1
         1: istore_0
         2: iconst_2
         3: istore_1
         4: iload_0
         5: iload_1
         6: iadd
         7: i2b
         8: istore_2
         9: iconst_4
        10: istore_3
        11: iconst_5
        12: istore        4
        14: iload_3
        15: iload         4
        17: imul
        18: i2s
        19: istore        5
        21: bipush        10
        23: istore        6
        25: iconst_5
        26: istore        7
        28: iload         6
        30: iload         7
        32: idiv
        33: istore        8
        35: ldc2_w        #8                  // long 50l
        38: lstore        9
        40: ldc2_w        #10                 // long 30l
        43: lstore        11
        45: lload         9
        47: lload         11
        49: lsub
        50: lstore        13
        52: return
      LineNumberTable:
        line 28: 0
        line 29: 2
        line 30: 4
        line 32: 9
        line 33: 11
        line 34: 14
        line 36: 21
        line 37: 25
        line 38: 28
        line 40: 35
        line 41: 40
        line 42: 45
        line 43: 52
}
SourceFile: "Hello.java"
